[
  {
    "packageName": "com.skystream-nsfw.allstreampron",
    "name": "Allstreampron",
    "version": 1,
    "baseUrl": "https://allpornstream.com",
    "description": "Free Premium Porn Movies in Full Length from biggest Premium Porn Sites: MYLF, Brazzers, BLACKED, TeamSkeet and many more!",
    "authors": [
      "techmind09"
    ],
    "languages": [
      "en"
    ],
    "categories": [
      "NSFW"
    ],
    "isAdult": true,
    "url": "https://raw.githubusercontent.com/techmind09/skystream-nsfw/repo/dist/com.skystream-nsfw.allstreampron.sky"
  },
  {
    "packageName": "com.skystream-nsfw.beeg24",
    "name": "Beeg24",
    "version": 1,
    "baseUrl": "https://beeg24.org",
    "description": "Beeg24 Site for 18+",
    "isAdult": true,
    "authors": [
      "techmind09"
    ],
    "languages": [
      "en"
    ],
    "categories": [
      "Adult"
    ],
    "url": "https://raw.githubusercontent.com/techmind09/skystream-nsfw/repo/dist/com.skystream-nsfw.beeg24.sky"
  },
  {
    "packageName": "com.skystream-nsfw.Wow",
    "name": "Wow",
    "version": 1,
    "baseUrl": "https://www.wow.xxx",
    "description": "Wow Site for 18+",
    "isAdult": true,
    "authors": [
      "techmind09"
    ],
    "languages": [
      "en"
    ],
    "categories": [
      "Adult"
    ],
    "url": "https://raw.githubusercontent.com/techmind09/skystream-nsfw/repo/dist/com.skystream-nsfw.Wow.sky"
  },
  {
    "packageName": "com.skystream-nsfw.xmoviesforyou",
    "name": "Xmoviesforyou",
    "version": 1,
    "baseUrl": "https://xmoviesforyou.com",
    "description": "Free Premium Porn Movies in Full Length from biggest Premium Porn Sites: MYLF, Brazzers, BLACKED, TeamSkeet and many more!",
    "authors": [
      "techmind09"
    ],
    "languages": [
      "en"
    ],
    "categories": [
      "NSFW"
    ],
    "isAdult": true,
    "url": "https://raw.githubusercontent.com/techmind09/skystream-nsfw/repo/dist/com.skystream-nsfw.xmoviesforyou.sky"
  },
  {
    "packageName": "com.skystream-nsfw.youperv",
    "name": "Youperv",
    "version": 1,
    "baseUrl": "https://youperv.com",
    "description": "Youperv Site for 18+",
    "isAdult": true,
    "authors": [
      "techmind09"
    ],
    "languages": [
      "en"
    ],
    "categories": [
      "Adult"
    ],
    "url": "https://raw.githubusercontent.com/techmind09/skystream-nsfw/repo/dist/com.skystream-nsfw.youperv.sky"
  }
]
